murt/__init__.py
murt/calculator.cpython-38-darwin.so
murt/core.cpython-38-darwin.so
murt/apps/__init__.py
murt/apps/scene_randomer.py
murt/core/calculator.cpp
murt/core/core.cpp
murt/engine/__init__.py
murt/engine/mtracer.py
murt/utils/__init__.py
murt/utils/generator.py
murt/utils/object.py
murt/utils/objreader.py
murt/window/__init__.py
murt/window/mwindow.py
murt-0.0.6.data/data/murt-assets/cube.mtl
murt-0.0.6.data/data/murt-assets/cube.obj
murt-0.0.6.data/data/murt-assets/ground.mtl
murt-0.0.6.data/data/murt-assets/ground.obj
murt-0.0.6.data/data/murt-assets/house.mtl
murt-0.0.6.data/data/murt-assets/house.obj
murt-0.0.6.data/data/murt-assets/poznan.obj
murt-0.0.6.dist-info/LICENSE
murt-0.0.6.dist-info/METADATA
murt-0.0.6.dist-info/WHEEL
murt-0.0.6.dist-info/top_level.txt
murt-0.0.6.dist-info/RECORD
