Metadata-Version: 2.1
Name: murt
Version: 0.0.6
Summary: Python Library for Multipath Ray Tracing
Home-page: UNKNOWN
Author: Supawat Tamsri
Author-email: contact@supawat.dev
License: MIT
Keywords: Telecommunications,Radio,Ray Tracing,Simulation
Platform: UNKNOWN
Requires-Python: >=3.7.10
Requires-Dist: wheel
Requires-Dist: numpy (>=1.20.2)
Requires-Dist: pyglet
Requires-Dist: pywavefront
